hecaton/__init__.py
hecaton/help.txt
hecaton/logo_hecaton.txt
hecaton/serverless.py
hecaton/client/__init__.py
hecaton/client/argparser.py
hecaton/client/cli.py
hecaton/client/managers/__init__.py
hecaton/client/managers/api.py
hecaton/client/managers/db.py
hecaton/client/managers/image.py
hecaton/client/managers/job.py
hecaton/client/managers/server.py
hecaton/client/managers/user.py
hecaton/client/managers/worker.py
hecaton/gpu/argparser.py
hecaton/gpu/docker_manager.py
hecaton/gpu/main.py
hecaton/gpu/utils.py
hecaton/gpu/web_client.py
hecaton/gpu/worker.py
hecaton/server/argparser.py
hecaton/server/auth.py
hecaton/server/dto.py
hecaton/server/main.py
hecaton/server/worker.py
hecaton-0.6.4.dist-info/METADATA
hecaton-0.6.4.dist-info/WHEEL
hecaton-0.6.4.dist-info/entry_points.txt
hecaton-0.6.4.dist-info/top_level.txt
hecaton-0.6.4.dist-info/RECORD
