Metadata-Version: 2.4
Name: hecaton
Version: 0.6.4
Summary: Hecaton distributed compute framework
Author-email: Just1duc <aworld068@gmail.com>
Requires-Python: >=3.9
Requires-Dist: fastapi
Requires-Dist: uvicorn
Requires-Dist: platformdirs
Requires-Dist: typer
Requires-Dist: prompt_toolkit
Requires-Dist: click
Requires-Dist: docker
Requires-Dist: python-dotenv
Requires-Dist: python-jose
Requires-Dist: passlib
Requires-Dist: fastapi-utilities
Requires-Dist: python-multipart
